LICENSE
MANIFEST.in
README.rst
setup.py
ipster/__init__.py
ipster/command_line.py
ipster/post_0_11.py
ipster/since_5.py
ipython_agnoster.egg-info/PKG-INFO
ipython_agnoster.egg-info/SOURCES.txt
ipython_agnoster.egg-info/dependency_links.txt
ipython_agnoster.egg-info/entry_points.txt
ipython_agnoster.egg-info/not-zip-safe
ipython_agnoster.egg-info/requires.txt
ipython_agnoster.egg-info/top_level.txt