Metadata-Version: 1.1
Name: ipython-agnoster
Version: 0.0.9
Summary: A hipster theme for the IPython REPL
Home-page: https://github.com/i5ar/ipster
Author: Pierpaolo Rasicci
Author-email: UNKNOWN
License: MIT
Keywords: ipython agnoster
Platform: UNKNOWN
Classifier: Development Status :: 1 - Planning
Classifier: Environment :: Console
Classifier: Framework :: IPython
Classifier: Intended Audience :: Developers
Classifier: Intended Audience :: Science/Research
Classifier: Intended Audience :: System Administrators
Classifier: License :: OSI Approved :: MIT License
Classifier: Operating System :: MacOS
Classifier: Operating System :: POSIX
Classifier: Programming Language :: Python
Classifier: Topic :: Text Editors
